{ "backgroundcolor":"#000000",
 "height":80,
 "infinite":false,
 "layers":[
        {
         "compression":"zlib",
         "data":"eJzt2MGNgkAUgGF62Ast0MVW4WnLoAALMrSwR9pSEzY7skxmwI0Pw3f4Yp4m5vkHMurYNM0IAAAAAAAAAABAiO+Novfei1yffqLftn6nyVH79Svk2uUarnnv6A5bXWafYyjMlf3OfWIoz+Ednun3lRgq5lK\/e5\/0+Yo5vMN\/9vu4aadH\/fR7db+o+\/eS2S+6Ualflxgq5p9O3Uzar0tUzIu7dPodot+a72nu37\/7tc3vebGkTTg\/9nv9vaP5+Vui33PXn99vj\/x\/8Bq3Hp9LknaLr0fvvRe5Pv1Ev239SqL3BgAAAAAAAAAAIM4VNIT50Q==",
         "encoding":"base64",
         "height":80,
         "name":"back",
         "opacity":0.5,
         "type":"tilelayer",
         "visible":true,
         "width":80,
         "x":0,
         "y":0
        }, 
        {
         "compression":"zlib",
         "data":"eJzt2d2NgkAUgFGswDq2P3vyBbeFLQ1DlETNDs6AxHvDOcl9kTDRL4M\/2HUAAAAAAAAAAHH8PUzLMZ771MwetDbZYjK7VM7SNrXrZrW0y6kwe9uHpQ5zXd6p6Vzqnc1We2Qv+7B2\/502XDtzw99vP4G7qVvf5WoYsd+5y9Mwar8sDSP3y3AtR+g3NRqb\/bxM9H0YrV\/\/8HiG98Kx3\/HQNv3MOXPHSpO5XwSZr98osn5+RJH1+0sUWb8\/R5H199vr+3Vpxtc1NKw73M+pWTvz\/YPWe0s1DYcF62ZsN3L\/dJ2le8T9+xv\/H62zZr98avZCl\/Xm+mgHAAAAAAAAAPC\/K9RlUCs=",
         "encoding":"base64",
         "height":80,
         "name":"front",
         "opacity":1,
         "type":"tilelayer",
         "visible":true,
         "width":80,
         "x":0,
         "y":0
        }, 
        {
         "color":"#5555ff",
         "draworder":"topdown",
         "name":"mods",
         "objects":[
                {
                 "height":8,
                 "id":1866,
                 "name":"",
                 "properties":
                    {
                     "back":"slopedhullpanel",
                     "colorVariant":"3",
                     "front":"slopedhullpanel"
                    },
                 "propertytypes":
                    {
                     "back":"string",
                     "colorVariant":"string",
                     "front":"string"
                    },
                 "rotation":0,
                 "type":"",
                 "visible":true,
                 "width":264,
                 "x":56,
                 "y":408
                }, 
                {
                 "height":8,
                 "id":1867,
                 "name":"",
                 "properties":
                    {
                     "back":"slopedhullpanel",
                     "colorVariant":"3",
                     "front":"slopedhullpanel"
                    },
                 "propertytypes":
                    {
                     "back":"string",
                     "colorVariant":"string",
                     "front":"string"
                    },
                 "rotation":0,
                 "type":"",
                 "visible":true,
                 "width":112,
                 "x":56,
                 "y":392
                }, 
                {
                 "height":8,
                 "id":1869,
                 "name":"",
                 "properties":
                    {
                     "back":"heavypipe",
                     "colorVariant":"7",
                     "front":"heavypipe"
                    },
                 "propertytypes":
                    {
                     "back":"string",
                     "colorVariant":"string",
                     "front":"string"
                    },
                 "rotation":0,
                 "type":"",
                 "visible":true,
                 "width":80,
                 "x":56,
                 "y":400
                }, 
                {
                 "height":8,
                 "id":1870,
                 "name":"",
                 "properties":
                    {
                     "back":"outpostwall2",
                     "colorVariant":"8",
                     "front":"outpostwall2"
                    },
                 "propertytypes":
                    {
                     "back":"string",
                     "colorVariant":"string",
                     "front":"string"
                    },
                 "rotation":0,
                 "type":"",
                 "visible":true,
                 "width":80,
                 "x":56,
                 "y":384
                }, 
                {
                 "height":8,
                 "id":1872,
                 "name":"",
                 "properties":
                    {
                     "back":"slopedhullpanel",
                     "colorVariant":"3",
                     "front":"slopedhullpanel"
                    },
                 "propertytypes":
                    {
                     "back":"string",
                     "colorVariant":"string",
                     "front":"string"
                    },
                 "rotation":0,
                 "type":"",
                 "visible":true,
                 "width":96,
                 "x":56,
                 "y":376
                }, 
                {
                 "height":8,
                 "id":1921,
                 "name":"",
                 "properties":
                    {
                     "back":"outpostwall2",
                     "colorVariant":"8"
                    },
                 "propertytypes":
                    {
                     "back":"string",
                     "colorVariant":"string"
                    },
                 "rotation":0,
                 "type":"",
                 "visible":true,
                 "width":16,
                 "x":184,
                 "y":384
                }, 
                {
                 "height":8,
                 "id":1928,
                 "name":"",
                 "properties":
                    {
                     "back":"heavypipe",
                     "colorVariant":"7",
                     "front":"heavypipe"
                    },
                 "propertytypes":
                    {
                     "back":"string",
                     "colorVariant":"string",
                     "front":"string"
                    },
                 "rotation":0,
                 "type":"",
                 "visible":true,
                 "width":80,
                 "x":56,
                 "y":232
                }, 
                {
                 "height":8,
                 "id":1929,
                 "name":"",
                 "properties":
                    {
                     "back":"slopedhullpanel",
                     "colorVariant":"3",
                     "front":"slopedhullpanel"
                    },
                 "propertytypes":
                    {
                     "back":"string",
                     "colorVariant":"string",
                     "front":"string"
                    },
                 "rotation":0,
                 "type":"",
                 "visible":true,
                 "width":112,
                 "x":56,
                 "y":240
                }, 
                {
                 "height":8,
                 "id":1930,
                 "name":"",
                 "properties":
                    {
                     "back":"slopedhullpanel",
                     "colorVariant":"3",
                     "front":"slopedhullpanel"
                    },
                 "propertytypes":
                    {
                     "back":"string",
                     "colorVariant":"string",
                     "front":"string"
                    },
                 "rotation":0,
                 "type":"",
                 "visible":true,
                 "width":96,
                 "x":56,
                 "y":256
                }, 
                {
                 "height":8,
                 "id":1931,
                 "name":"",
                 "properties":
                    {
                     "back":"slopedhullpanel",
                     "colorVariant":"3",
                     "front":"slopedhullpanel"
                    },
                 "propertytypes":
                    {
                     "back":"string",
                     "colorVariant":"string",
                     "front":"string"
                    },
                 "rotation":0,
                 "type":"",
                 "visible":true,
                 "width":264,
                 "x":56,
                 "y":224
                }, 
                {
                 "height":8,
                 "id":1932,
                 "name":"",
                 "properties":
                    {
                     "back":"outpostwall2",
                     "colorVariant":"8",
                     "front":"outpostwall2"
                    },
                 "propertytypes":
                    {
                     "back":"string",
                     "colorVariant":"string",
                     "front":"string"
                    },
                 "rotation":0,
                 "type":"",
                 "visible":true,
                 "width":80,
                 "x":56,
                 "y":248
                }, 
                {
                 "height":8,
                 "id":1933,
                 "name":"",
                 "properties":
                    {
                     "back":"outpostwall2",
                     "colorVariant":"8"
                    },
                 "propertytypes":
                    {
                     "back":"string",
                     "colorVariant":"string"
                    },
                 "rotation":0,
                 "type":"",
                 "visible":true,
                 "width":16,
                 "x":184,
                 "y":248
                }, 
                {
                 "height":8,
                 "id":1934,
                 "name":"",
                 "properties":
                    {
                     "colorVariant":"8",
                     "front":"outpostwall2"
                    },
                 "propertytypes":
                    {
                     "colorVariant":"string",
                     "front":"string"
                    },
                 "rotation":0,
                 "type":"",
                 "visible":true,
                 "width":48,
                 "x":168,
                 "y":240
                }, 
                {
                 "height":8,
                 "id":1935,
                 "name":"",
                 "properties":
                    {
                     "colorVariant":"8",
                     "front":"outpostwall2"
                    },
                 "propertytypes":
                    {
                     "colorVariant":"string",
                     "front":"string"
                    },
                 "rotation":0,
                 "type":"",
                 "visible":true,
                 "width":48,
                 "x":168,
                 "y":392
                }, 
                {
                 "height":8,
                 "id":1936,
                 "name":"",
                 "properties":
                    {
                     "back":"slopedhullpanel",
                     "colorVariant":"7"
                    },
                 "propertytypes":
                    {
                     "back":"string",
                     "colorVariant":"string"
                    },
                 "rotation":0,
                 "type":"",
                 "visible":true,
                 "width":24,
                 "x":200,
                 "y":384
                }, 
                {
                 "height":8,
                 "id":1937,
                 "name":"",
                 "properties":
                    {
                     "back":"slopedhullpanel",
                     "colorVariant":"7"
                    },
                 "propertytypes":
                    {
                     "back":"string",
                     "colorVariant":"string"
                    },
                 "rotation":0,
                 "type":"",
                 "visible":true,
                 "width":32,
                 "x":200,
                 "y":376
                }, 
                {
                 "height":8,
                 "id":1938,
                 "name":"",
                 "properties":
                    {
                     "back":"slopedhullpanel",
                     "colorVariant":"7"
                    },
                 "propertytypes":
                    {
                     "back":"string",
                     "colorVariant":"string"
                    },
                 "rotation":0,
                 "type":"",
                 "visible":true,
                 "width":24,
                 "x":208,
                 "y":360
                }, 
                {
                 "height":8,
                 "id":1939,
                 "name":"",
                 "properties":
                    {
                     "back":"slopedhullpanel",
                     "colorVariant":"7"
                    },
                 "propertytypes":
                    {
                     "back":"string",
                     "colorVariant":"string"
                    },
                 "rotation":0,
                 "type":"",
                 "visible":true,
                 "width":32,
                 "x":208,
                 "y":368
                }, 
                {
                 "height":64,
                 "id":1940,
                 "name":"",
                 "properties":
                    {
                     "back":"slopedhullpanel",
                     "colorVariant":"7"
                    },
                 "propertytypes":
                    {
                     "back":"string",
                     "colorVariant":"string"
                    },
                 "rotation":0,
                 "type":"",
                 "visible":true,
                 "width":16,
                 "x":208,
                 "y":288
                }, 
                {
                 "height":8,
                 "id":1941,
                 "name":"",
                 "properties":
                    {
                     "back":"slopedhullpanel",
                     "colorVariant":"7"
                    },
                 "propertytypes":
                    {
                     "back":"string",
                     "colorVariant":"string"
                    },
                 "rotation":0,
                 "type":"",
                 "visible":true,
                 "width":24,
                 "x":208,
                 "y":272
                }, 
                {
                 "height":8,
                 "id":1942,
                 "name":"",
                 "properties":
                    {
                     "back":"slopedhullpanel",
                     "colorVariant":"7",
                     "front":"compositerail"
                    },
                 "propertytypes":
                    {
                     "back":"string",
                     "colorVariant":"string",
                     "front":"string"
                    },
                 "rotation":0,
                 "type":"",
                 "visible":true,
                 "width":32,
                 "x":208,
                 "y":264
                }, 
                {
                 "height":8,
                 "id":1943,
                 "name":"",
                 "properties":
                    {
                     "back":"slopedhullpanel",
                     "colorVariant":"7"
                    },
                 "propertytypes":
                    {
                     "back":"string",
                     "colorVariant":"string"
                    },
                 "rotation":0,
                 "type":"",
                 "visible":true,
                 "width":32,
                 "x":200,
                 "y":256
                }, 
                {
                 "height":8,
                 "id":1944,
                 "name":"",
                 "properties":
                    {
                     "back":"slopedhullpanel",
                     "colorVariant":"7"
                    },
                 "propertytypes":
                    {
                     "back":"string",
                     "colorVariant":"string"
                    },
                 "rotation":0,
                 "type":"",
                 "visible":true,
                 "width":24,
                 "x":200,
                 "y":248
                }, 
                {
                 "height":8,
                 "id":1945,
                 "name":"",
                 "properties":
                    {
                     "back":"slopedhullpanel",
                     "colorVariant":"7"
                    },
                 "propertytypes":
                    {
                     "back":"string",
                     "colorVariant":"string"
                    },
                 "rotation":0,
                 "type":"",
                 "visible":true,
                 "width":24,
                 "x":160,
                 "y":248
                }, 
                {
                 "height":8,
                 "id":1946,
                 "name":"",
                 "properties":
                    {
                     "back":"slopedhullpanel",
                     "colorVariant":"7"
                    },
                 "propertytypes":
                    {
                     "back":"string",
                     "colorVariant":"string"
                    },
                 "rotation":0,
                 "type":"",
                 "visible":true,
                 "width":32,
                 "x":152,
                 "y":256
                }, 
                {
                 "height":8,
                 "id":1950,
                 "name":"",
                 "properties":
                    {
                     "back":"slopedhullpanel",
                     "colorVariant":"7"
                    },
                 "propertytypes":
                    {
                     "back":"string",
                     "colorVariant":"string"
                    },
                 "rotation":0,
                 "type":"",
                 "visible":true,
                 "width":24,
                 "x":152,
                 "y":272
                }, 
                {
                 "height":64,
                 "id":1951,
                 "name":"",
                 "properties":
                    {
                     "back":"slopedhullpanel",
                     "colorVariant":"7"
                    },
                 "propertytypes":
                    {
                     "back":"string",
                     "colorVariant":"string"
                    },
                 "rotation":0,
                 "type":"",
                 "visible":true,
                 "width":16,
                 "x":160,
                 "y":288
                }, 
                {
                 "height":8,
                 "id":1952,
                 "name":"",
                 "properties":
                    {
                     "back":"slopedhullpanel",
                     "colorVariant":"7"
                    },
                 "propertytypes":
                    {
                     "back":"string",
                     "colorVariant":"string"
                    },
                 "rotation":0,
                 "type":"",
                 "visible":true,
                 "width":24,
                 "x":152,
                 "y":360
                }, 
                {
                 "height":8,
                 "id":1953,
                 "name":"",
                 "properties":
                    {
                     "back":"slopedhullpanel",
                     "colorVariant":"7"
                    },
                 "propertytypes":
                    {
                     "back":"string",
                     "colorVariant":"string"
                    },
                 "rotation":0,
                 "type":"",
                 "visible":true,
                 "width":32,
                 "x":144,
                 "y":368
                }, 
                {
                 "height":8,
                 "id":1954,
                 "name":"",
                 "properties":
                    {
                     "back":"slopedhullpanel",
                     "colorVariant":"7"
                    },
                 "propertytypes":
                    {
                     "back":"string",
                     "colorVariant":"string"
                    },
                 "rotation":0,
                 "type":"",
                 "visible":true,
                 "width":32,
                 "x":152,
                 "y":376
                }, 
                {
                 "height":8,
                 "id":1955,
                 "name":"",
                 "properties":
                    {
                     "back":"slopedhullpanel",
                     "colorVariant":"7"
                    },
                 "propertytypes":
                    {
                     "back":"string",
                     "colorVariant":"string"
                    },
                 "rotation":0,
                 "type":"",
                 "visible":true,
                 "width":24,
                 "x":160,
                 "y":384
                }, 
                {
                 "height":8,
                 "id":1956,
                 "name":"",
                 "properties":
                    {
                     "back":"slopedhullpanel",
                     "colorVariant":"3",
                     "front":"slopedhullpanel"
                    },
                 "propertytypes":
                    {
                     "back":"string",
                     "colorVariant":"string",
                     "front":"string"
                    },
                 "rotation":0,
                 "type":"",
                 "visible":true,
                 "width":24,
                 "x":152,
                 "y":424
                }, 
                {
                 "height":8,
                 "id":1957,
                 "name":"",
                 "properties":
                    {
                     "back":"slopedhullpanel",
                     "colorVariant":"3",
                     "front":"slopedhullpanel"
                    },
                 "propertytypes":
                    {
                     "back":"string",
                     "colorVariant":"string",
                     "front":"string"
                    },
                 "rotation":0,
                 "type":"",
                 "visible":true,
                 "width":96,
                 "x":144,
                 "y":416
                }, 
                {
                 "height":8,
                 "id":1958,
                 "name":"",
                 "properties":
                    {
                     "back":"slopedhullpanel",
                     "colorVariant":"3",
                     "front":"slopedhullpanel"
                    },
                 "propertytypes":
                    {
                     "back":"string",
                     "colorVariant":"string",
                     "front":"string"
                    },
                 "rotation":0,
                 "type":"",
                 "visible":true,
                 "width":120,
                 "x":232,
                 "y":376
                }, 
                {
                 "height":8,
                 "id":1959,
                 "name":"",
                 "properties":
                    {
                     "back":"slopedhullpanel",
                     "colorVariant":"3",
                     "front":"slopedhullpanel"
                    },
                 "propertytypes":
                    {
                     "back":"string",
                     "colorVariant":"string",
                     "front":"string"
                    },
                 "rotation":0,
                 "type":"",
                 "visible":true,
                 "width":120,
                 "x":216,
                 "y":392
                }, 
                {
                 "height":8,
                 "id":1960,
                 "name":"",
                 "properties":
                    {
                     "back":"slopedhullpanel",
                     "colorVariant":"3",
                     "front":"slopedhullpanel"
                    },
                 "propertytypes":
                    {
                     "back":"string",
                     "colorVariant":"string",
                     "front":"string"
                    },
                 "rotation":0,
                 "type":"",
                 "visible":true,
                 "width":112,
                 "x":136,
                 "y":400
                }, 
                {
                 "height":8,
                 "id":1961,
                 "name":"",
                 "properties":
                    {
                     "back":"slopedhullpanel",
                     "colorVariant":"3",
                     "front":"slopedhullpanel"
                    },
                 "propertytypes":
                    {
                     "back":"string",
                     "colorVariant":"string",
                     "front":"string"
                    },
                 "rotation":0,
                 "type":"",
                 "visible":true,
                 "width":24,
                 "x":224,
                 "y":384
                }, 
                {
                 "height":8,
                 "id":1962,
                 "name":"",
                 "properties":
                    {
                     "back":"slopedhullpanel",
                     "colorVariant":"3",
                     "front":"slopedhullpanel"
                    },
                 "propertytypes":
                    {
                     "back":"string",
                     "colorVariant":"string",
                     "front":"string"
                    },
                 "rotation":0,
                 "type":"",
                 "visible":true,
                 "width":24,
                 "x":136,
                 "y":384
                }, 
                {
                 "height":8,
                 "id":1963,
                 "name":"",
                 "properties":
                    {
                     "back":"heavypipe",
                     "colorVariant":"7",
                     "front":"heavypipe"
                    },
                 "propertytypes":
                    {
                     "back":"string",
                     "colorVariant":"string",
                     "front":"string"
                    },
                 "rotation":0,
                 "type":"",
                 "visible":true,
                 "width":64,
                 "x":248,
                 "y":400
                }, 
                {
                 "height":8,
                 "id":1964,
                 "name":"",
                 "properties":
                    {
                     "back":"outpostwall2",
                     "colorVariant":"8",
                     "front":"outpostwall2"
                    },
                 "propertytypes":
                    {
                     "back":"string",
                     "colorVariant":"string",
                     "front":"string"
                    },
                 "rotation":0,
                 "type":"",
                 "visible":true,
                 "width":64,
                 "x":248,
                 "y":384
                }, 
                {
                 "height":8,
                 "id":1965,
                 "name":"",
                 "properties":
                    {
                     "back":"slopedhullpanel",
                     "colorVariant":"3",
                     "front":"slopedhullpanel"
                    },
                 "propertytypes":
                    {
                     "back":"string",
                     "colorVariant":"string",
                     "front":"string"
                    },
                 "rotation":0,
                 "type":"",
                 "visible":true,
                 "width":24,
                 "x":152,
                 "y":208
                }, 
                {
                 "height":8,
                 "id":1966,
                 "name":"",
                 "properties":
                    {
                     "back":"slopedhullpanel",
                     "colorVariant":"3",
                     "front":"slopedhullpanel"
                    },
                 "propertytypes":
                    {
                     "back":"string",
                     "colorVariant":"string",
                     "front":"string"
                    },
                 "rotation":0,
                 "type":"",
                 "visible":true,
                 "width":96,
                 "x":144,
                 "y":216
                }, 
                {
                 "height":8,
                 "id":1967,
                 "name":"",
                 "properties":
                    {
                     "back":"slopedhullpanel",
                     "colorVariant":"3",
                     "front":"slopedhullpanel"
                    },
                 "propertytypes":
                    {
                     "back":"string",
                     "colorVariant":"string",
                     "front":"string"
                    },
                 "rotation":0,
                 "type":"",
                 "visible":true,
                 "width":112,
                 "x":136,
                 "y":232
                }, 
                {
                 "height":8,
                 "id":1968,
                 "name":"",
                 "properties":
                    {
                     "back":"slopedhullpanel",
                     "colorVariant":"3",
                     "front":"slopedhullpanel"
                    },
                 "propertytypes":
                    {
                     "back":"string",
                     "colorVariant":"string",
                     "front":"string"
                    },
                 "rotation":0,
                 "type":"",
                 "visible":true,
                 "width":24,
                 "x":136,
                 "y":248
                }, 
                {
                 "height":8,
                 "id":1969,
                 "name":"",
                 "properties":
                    {
                     "back":"slopedhullpanel",
                     "colorVariant":"3",
                     "front":"slopedhullpanel"
                    },
                 "propertytypes":
                    {
                     "back":"string",
                     "colorVariant":"string",
                     "front":"string"
                    },
                 "rotation":0,
                 "type":"",
                 "visible":true,
                 "width":24,
                 "x":224,
                 "y":248
                }, 
                {
                 "height":8,
                 "id":1970,
                 "name":"",
                 "properties":
                    {
                     "back":"slopedhullpanel",
                     "colorVariant":"3",
                     "front":"slopedhullpanel"
                    },
                 "propertytypes":
                    {
                     "back":"string",
                     "colorVariant":"string",
                     "front":"string"
                    },
                 "rotation":0,
                 "type":"",
                 "visible":true,
                 "width":120,
                 "x":216,
                 "y":240
                }, 
                {
                 "height":8,
                 "id":1971,
                 "name":"",
                 "properties":
                    {
                     "back":"slopedhullpanel",
                     "colorVariant":"3",
                     "front":"slopedhullpanel"
                    },
                 "propertytypes":
                    {
                     "back":"string",
                     "colorVariant":"string",
                     "front":"string"
                    },
                 "rotation":0,
                 "type":"",
                 "visible":true,
                 "width":120,
                 "x":232,
                 "y":256
                }, 
                {
                 "height":8,
                 "id":1974,
                 "name":"",
                 "properties":
                    {
                     "back":"slopedhullpanel",
                     "colorVariant":"3",
                     "front":"slopedhullpanel"
                    },
                 "propertytypes":
                    {
                     "back":"string",
                     "colorVariant":"string",
                     "front":"string"
                    },
                 "rotation":0,
                 "type":"",
                 "visible":true,
                 "width":32,
                 "x":312,
                 "y":384
                }, 
                {
                 "height":8,
                 "id":1975,
                 "name":"",
                 "properties":
                    {
                     "back":"slopedhullpanel",
                     "colorVariant":"3",
                     "front":"slopedhullpanel"
                    },
                 "propertytypes":
                    {
                     "back":"string",
                     "colorVariant":"string",
                     "front":"string"
                    },
                 "rotation":0,
                 "type":"",
                 "visible":true,
                 "width":16,
                 "x":312,
                 "y":400
                }, 
                {
                 "height":8,
                 "id":1976,
                 "name":"",
                 "properties":
                    {
                     "back":"slopedhullpanel",
                     "colorVariant":"3",
                     "front":"slopedhullpanel"
                    },
                 "propertytypes":
                    {
                     "back":"string",
                     "colorVariant":"string",
                     "front":"string"
                    },
                 "rotation":0,
                 "type":"",
                 "visible":true,
                 "width":32,
                 "x":312,
                 "y":248
                }, 
                {
                 "height":8,
                 "id":1977,
                 "name":"",
                 "properties":
                    {
                     "back":"outpostwall2",
                     "colorVariant":"8",
                     "front":"outpostwall2"
                    },
                 "propertytypes":
                    {
                     "back":"string",
                     "colorVariant":"string",
                     "front":"string"
                    },
                 "rotation":0,
                 "type":"",
                 "visible":true,
                 "width":64,
                 "x":248,
                 "y":248
                }, 
                {
                 "height":8,
                 "id":1978,
                 "name":"",
                 "properties":
                    {
                     "back":"slopedhullpanel",
                     "colorVariant":"3",
                     "front":"slopedhullpanel"
                    },
                 "propertytypes":
                    {
                     "back":"string",
                     "colorVariant":"string",
                     "front":"string"
                    },
                 "rotation":0,
                 "type":"",
                 "visible":true,
                 "width":16,
                 "x":312,
                 "y":232
                }, 
                {
                 "height":8,
                 "id":1979,
                 "name":"",
                 "properties":
                    {
                     "back":"heavypipe",
                     "colorVariant":"7",
                     "front":"heavypipe"
                    },
                 "propertytypes":
                    {
                     "back":"string",
                     "colorVariant":"string",
                     "front":"string"
                    },
                 "rotation":0,
                 "type":"",
                 "visible":true,
                 "width":64,
                 "x":248,
                 "y":232
                }, 
                {
                 "height":8,
                 "id":1980,
                 "name":"",
                 "properties":
                    {
                     "back":"slopedhullpanel",
                     "colorVariant":"3",
                     "front":"slopedhullpanel"
                    },
                 "propertytypes":
                    {
                     "back":"string",
                     "colorVariant":"string",
                     "front":"string"
                    },
                 "rotation":0,
                 "type":"",
                 "visible":true,
                 "width":40,
                 "x":320,
                 "y":368
                }, 
                {
                 "height":8,
                 "id":1981,
                 "name":"",
                 "properties":
                    {
                     "back":"slopedhullpanel",
                     "colorVariant":"3",
                     "front":"slopedhullpanel"
                    },
                 "propertytypes":
                    {
                     "back":"string",
                     "colorVariant":"string",
                     "front":"string"
                    },
                 "rotation":0,
                 "type":"",
                 "visible":true,
                 "width":40,
                 "x":320,
                 "y":264
                }, 
                {
                 "height":32,
                 "id":1982,
                 "name":"",
                 "properties":
                    {
                     "back":"slopedhullpanel",
                     "colorVariant":"3",
                     "front":"slopedhullpanel"
                    },
                 "propertytypes":
                    {
                     "back":"string",
                     "colorVariant":"string",
                     "front":"string"
                    },
                 "rotation":0,
                 "type":"",
                 "visible":true,
                 "width":16,
                 "x":328,
                 "y":272
                }, 
                {
                 "height":32,
                 "id":1983,
                 "name":"",
                 "properties":
                    {
                     "back":"slopedhullpanel",
                     "colorVariant":"3",
                     "front":"slopedhullpanel"
                    },
                 "propertytypes":
                    {
                     "back":"string",
                     "colorVariant":"string",
                     "front":"string"
                    },
                 "rotation":0,
                 "type":"",
                 "visible":true,
                 "width":16,
                 "x":328,
                 "y":336
                }, 
                {
                 "height":32,
                 "id":1988,
                 "name":"",
                 "properties":
                    {
                     "back":"outpostwall1",
                     "colorVariant":"7"
                    },
                 "propertytypes":
                    {
                     "back":"string",
                     "colorVariant":"string"
                    },
                 "rotation":0,
                 "type":"",
                 "visible":true,
                 "width":24,
                 "x":128,
                 "y":280
                }, 
                {
                 "height":8,
                 "id":1989,
                 "name":"",
                 "properties":
                    {
                     "back":"outpostwall1",
                     "colorVariant":"7"
                    },
                 "propertytypes":
                    {
                     "back":"string",
                     "colorVariant":"string"
                    },
                 "rotation":0,
                 "type":"",
                 "visible":true,
                 "width":24,
                 "x":96,
                 "y":304
                }, 
                {
                 "height":32,
                 "id":1991,
                 "name":"",
                 "properties":
                    {
                     "back":"outpostwall1",
                     "colorVariant":"7"
                    },
                 "propertytypes":
                    {
                     "back":"string",
                     "colorVariant":"string"
                    },
                 "rotation":0,
                 "type":"",
                 "visible":true,
                 "width":24,
                 "x":64,
                 "y":280
                }, 
                {
                 "height":8,
                 "id":1992,
                 "name":"",
                 "properties":
                    {
                     "back":"outpostwall1",
                     "colorVariant":"1"
                    },
                 "propertytypes":
                    {
                     "back":"string",
                     "colorVariant":"string"
                    },
                 "rotation":0,
                 "type":"",
                 "visible":true,
                 "width":88,
                 "x":64,
                 "y":352
                }, 
                {
                 "height":8,
                 "id":1993,
                 "name":"",
                 "properties":
                    {
                     "back":"slopedhullpanel",
                     "colorVariant":"3",
                     "front":"slopedhullpanel"
                    },
                 "propertytypes":
                    {
                     "back":"string",
                     "colorVariant":"string",
                     "front":"string"
                    },
                 "rotation":0,
                 "type":"",
                 "visible":true,
                 "width":24,
                 "x":208,
                 "y":424
                }, 
                {
                 "height":8,
                 "id":1994,
                 "name":"",
                 "properties":
                    {
                     "back":"slopedhullpanel",
                     "colorVariant":"3",
                     "front":"slopedhullpanel"
                    },
                 "propertytypes":
                    {
                     "back":"string",
                     "colorVariant":"string",
                     "front":"string"
                    },
                 "rotation":0,
                 "type":"",
                 "visible":true,
                 "width":24,
                 "x":208,
                 "y":208
                }, 
                {
                 "height":8,
                 "id":2001,
                 "name":"",
                 "properties":
                    {
                     "colorVariant":"1",
                     "front":"lunarbaseplatform"
                    },
                 "propertytypes":
                    {
                     "colorVariant":"string",
                     "front":"string"
                    },
                 "rotation":0,
                 "type":"",
                 "visible":true,
                 "width":96,
                 "x":64,
                 "y":320
                }, 
                {
                 "height":8,
                 "id":2002,
                 "name":"",
                 "properties":
                    {
                     "colorVariant":"1",
                     "front":"lunarbaseplatform"
                    },
                 "propertytypes":
                    {
                     "colorVariant":"string",
                     "front":"string"
                    },
                 "rotation":0,
                 "type":"",
                 "visible":true,
                 "width":96,
                 "x":224,
                 "y":320
                }, 
                {
                 "height":8,
                 "id":2014,
                 "name":"",
                 "properties":
                    {
                     "back":"outpostwall1",
                     "colorVariant":"7"
                    },
                 "propertytypes":
                    {
                     "back":"string",
                     "colorVariant":"string"
                    },
                 "rotation":0,
                 "type":"",
                 "visible":true,
                 "width":24,
                 "x":96,
                 "y":280
                }, 
                {
                 "height":8,
                 "id":2035,
                 "name":"",
                 "properties":
                    {
                     "back":"slopedhullpanel",
                     "colorVariant":"7",
                     "front":"compositerail"
                    },
                 "propertytypes":
                    {
                     "back":"string",
                     "colorVariant":"string",
                     "front":"string"
                    },
                 "rotation":0,
                 "type":"",
                 "visible":true,
                 "width":16,
                 "x":160,
                 "y":352
                }, 
                {
                 "height":8,
                 "id":2036,
                 "name":"",
                 "properties":
                    {
                     "back":"slopedhullpanel",
                     "colorVariant":"7",
                     "front":"compositerail"
                    },
                 "propertytypes":
                    {
                     "back":"string",
                     "colorVariant":"string",
                     "front":"string"
                    },
                 "rotation":0,
                 "type":"",
                 "visible":true,
                 "width":16,
                 "x":208,
                 "y":352
                }, 
                {
                 "height":8,
                 "id":2037,
                 "name":"",
                 "properties":
                    {
                     "back":"slopedhullpanel",
                     "colorVariant":"7",
                     "front":"compositerail"
                    },
                 "propertytypes":
                    {
                     "back":"string",
                     "colorVariant":"string",
                     "front":"string"
                    },
                 "rotation":0,
                 "type":"",
                 "visible":true,
                 "width":16,
                 "x":160,
                 "y":280
                }, 
                {
                 "height":8,
                 "id":2038,
                 "name":"",
                 "properties":
                    {
                     "back":"slopedhullpanel",
                     "colorVariant":"7",
                     "front":"compositerail"
                    },
                 "propertytypes":
                    {
                     "back":"string",
                     "colorVariant":"string",
                     "front":"string"
                    },
                 "rotation":0,
                 "type":"",
                 "visible":true,
                 "width":16,
                 "x":208,
                 "y":280
                }, 
                {
                 "height":8,
                 "id":2039,
                 "name":"",
                 "properties":
                    {
                     "back":"slopedhullpanel",
                     "colorVariant":"7",
                     "front":"compositerail"
                    },
                 "propertytypes":
                    {
                     "back":"string",
                     "colorVariant":"string",
                     "front":"string"
                    },
                 "rotation":0,
                 "type":"",
                 "visible":true,
                 "width":32,
                 "x":144,
                 "y":264
                }, 
                {
                 "height":32,
                 "id":2063,
                 "name":"",
                 "properties":
                    {
                     "back":"slopedhullpanel",
                     "colorVariant":"3",
                     "front":"slopedhullpanel"
                    },
                 "propertytypes":
                    {
                     "back":"string",
                     "colorVariant":"string",
                     "front":"string"
                    },
                 "rotation":0,
                 "type":"",
                 "visible":true,
                 "width":16,
                 "x":320,
                 "y":304
                }, 
                {
                 "height":32,
                 "id":2065,
                 "name":"",
                 "properties":
                    {
                     "back":"slopedhullpanel",
                     "colorVariant":"3",
                     "front":"slopedhullpanel"
                    },
                 "propertytypes":
                    {
                     "back":"string",
                     "colorVariant":"string",
                     "front":"string"
                    },
                 "rotation":0,
                 "type":"",
                 "visible":true,
                 "width":16,
                 "x":384,
                 "y":304
                }, 
                {
                 "height":8,
                 "id":2066,
                 "name":"",
                 "properties":
                    {
                     "back":"slopedhullpanel",
                     "colorVariant":"3",
                     "front":"slopedhullpanel"
                    },
                 "propertytypes":
                    {
                     "back":"string",
                     "colorVariant":"string",
                     "front":"string"
                    },
                 "rotation":0,
                 "type":"",
                 "visible":true,
                 "width":16,
                 "x":376,
                 "y":296
                }, 
                {
                 "height":8,
                 "id":2067,
                 "name":"",
                 "properties":
                    {
                     "back":"slopedhullpanel",
                     "colorVariant":"3",
                     "front":"slopedhullpanel"
                    },
                 "propertytypes":
                    {
                     "back":"string",
                     "colorVariant":"string",
                     "front":"string"
                    },
                 "rotation":0,
                 "type":"",
                 "visible":true,
                 "width":16,
                 "x":368,
                 "y":288
                }, 
                {
                 "height":8,
                 "id":2068,
                 "name":"",
                 "properties":
                    {
                     "back":"slopedhullpanel",
                     "colorVariant":"3",
                     "front":"slopedhullpanel"
                    },
                 "propertytypes":
                    {
                     "back":"string",
                     "colorVariant":"string",
                     "front":"string"
                    },
                 "rotation":0,
                 "type":"",
                 "visible":true,
                 "width":16,
                 "x":360,
                 "y":280
                }, 
                {
                 "height":8,
                 "id":2069,
                 "name":"",
                 "properties":
                    {
                     "back":"slopedhullpanel",
                     "colorVariant":"3",
                     "front":"slopedhullpanel"
                    },
                 "propertytypes":
                    {
                     "back":"string",
                     "colorVariant":"string",
                     "front":"string"
                    },
                 "rotation":0,
                 "type":"",
                 "visible":true,
                 "width":16,
                 "x":352,
                 "y":272
                }, 
                {
                 "height":8,
                 "id":2071,
                 "name":"",
                 "properties":
                    {
                     "back":"slopedhullpanel",
                     "colorVariant":"3",
                     "front":"slopedhullpanel"
                    },
                 "propertytypes":
                    {
                     "back":"string",
                     "colorVariant":"string",
                     "front":"string"
                    },
                 "rotation":0,
                 "type":"",
                 "visible":true,
                 "width":16,
                 "x":376,
                 "y":336
                }, 
                {
                 "height":8,
                 "id":2072,
                 "name":"",
                 "properties":
                    {
                     "back":"slopedhullpanel",
                     "colorVariant":"3",
                     "front":"slopedhullpanel"
                    },
                 "propertytypes":
                    {
                     "back":"string",
                     "colorVariant":"string",
                     "front":"string"
                    },
                 "rotation":0,
                 "type":"",
                 "visible":true,
                 "width":16,
                 "x":368,
                 "y":344
                }, 
                {
                 "height":8,
                 "id":2073,
                 "name":"",
                 "properties":
                    {
                     "back":"slopedhullpanel",
                     "colorVariant":"3",
                     "front":"slopedhullpanel"
                    },
                 "propertytypes":
                    {
                     "back":"string",
                     "colorVariant":"string",
                     "front":"string"
                    },
                 "rotation":0,
                 "type":"",
                 "visible":true,
                 "width":16,
                 "x":360,
                 "y":352
                }, 
                {
                 "height":8,
                 "id":2074,
                 "name":"",
                 "properties":
                    {
                     "back":"slopedhullpanel",
                     "colorVariant":"3",
                     "front":"slopedhullpanel"
                    },
                 "propertytypes":
                    {
                     "back":"string",
                     "colorVariant":"string",
                     "front":"string"
                    },
                 "rotation":0,
                 "type":"",
                 "visible":true,
                 "width":16,
                 "x":352,
                 "y":360
                }, 
                {
                 "height":32,
                 "id":2075,
                 "name":"",
                 "properties":
                    {
                     "colorVariant":"7",
                     "front":"apexshipsupport"
                    },
                 "propertytypes":
                    {
                     "colorVariant":"string",
                     "front":"string"
                    },
                 "rotation":0,
                 "type":"",
                 "visible":true,
                 "width":8,
                 "x":344,
                 "y":336
                }, 
                {
                 "height":32,
                 "id":2076,
                 "name":"",
                 "properties":
                    {
                     "colorVariant":"7",
                     "front":"apexshipsupport"
                    },
                 "propertytypes":
                    {
                     "colorVariant":"string",
                     "front":"string"
                    },
                 "rotation":0,
                 "type":"",
                 "visible":true,
                 "width":8,
                 "x":344,
                 "y":272
                }, 
                {
                 "height":8,
                 "id":2077,
                 "name":"",
                 "properties":
                    {
                     "colorVariant":"7",
                     "front":"apexshipsupport"
                    },
                 "propertytypes":
                    {
                     "colorVariant":"string",
                     "front":"string"
                    },
                 "rotation":0,
                 "type":"",
                 "visible":true,
                 "width":8,
                 "x":368,
                 "y":296
                }, 
                {
                 "height":8,
                 "id":2078,
                 "name":"",
                 "properties":
                    {
                     "colorVariant":"7",
                     "front":"apexshipsupport"
                    },
                 "propertytypes":
                    {
                     "colorVariant":"string",
                     "front":"string"
                    },
                 "rotation":0,
                 "type":"",
                 "visible":true,
                 "width":8,
                 "x":368,
                 "y":336
                }, 
                {
                 "height":16,
                 "id":2079,
                 "name":"",
                 "properties":
                    {
                     "colorVariant":"7",
                     "front":"apexshipsupport"
                    },
                 "propertytypes":
                    {
                     "colorVariant":"string",
                     "front":"string"
                    },
                 "rotation":0,
                 "type":"",
                 "visible":true,
                 "width":8,
                 "x":368,
                 "y":312
                }, 
                {
                 "height":16,
                 "id":2080,
                 "name":"",
                 "properties":
                    {
                     "colorVariant":"7",
                     "front":"apexshipsupport"
                    },
                 "propertytypes":
                    {
                     "colorVariant":"string",
                     "front":"string"
                    },
                 "rotation":0,
                 "type":"",
                 "visible":true,
                 "width":8,
                 "x":344,
                 "y":312
                }, 
                {
                 "height":8,
                 "id":2081,
                 "name":"",
                 "properties":
                    {
                     "colorVariant":"7",
                     "front":"apexshipdetails"
                    },
                 "propertytypes":
                    {
                     "colorVariant":"string",
                     "front":"string"
                    },
                 "rotation":0,
                 "type":"",
                 "visible":true,
                 "width":32,
                 "x":344,
                 "y":328
                }, 
                {
                 "height":8,
                 "id":2082,
                 "name":"",
                 "properties":
                    {
                     "colorVariant":"7",
                     "front":"apexshipdetails"
                    },
                 "propertytypes":
                    {
                     "colorVariant":"string",
                     "front":"string"
                    },
                 "rotation":0,
                 "type":"",
                 "visible":true,
                 "width":32,
                 "x":344,
                 "y":304
                }],
         "opacity":1,
         "type":"objectgroup",
         "visible":true,
         "x":0,
         "y":0
        }, 
        {
         "color":"#ff0000",
         "draworder":"topdown",
         "name":"objects",
         "objects":[
                {
                 "gid":8407,
                 "height":16,
                 "id":1918,
                 "name":"",
                 "rotation":0,
                 "type":"",
                 "visible":true,
                 "width":32,
                 "x":176,
                 "y":392
                }, 
                {
                 "gid":8411,
                 "height":32,
                 "id":1999,
                 "name":"",
                 "rotation":0,
                 "type":"",
                 "visible":true,
                 "width":16,
                 "x":160,
                 "y":392
                }, 
                {
                 "gid":2147492059,
                 "height":32,
                 "id":2000,
                 "name":"",
                 "rotation":0,
                 "type":"",
                 "visible":true,
                 "width":16,
                 "x":208,
                 "y":392
                }, 
                {
                 "gid":7551,
                 "height":24,
                 "id":2016,
                 "name":"",
                 "properties":
                    {
                     "parameters":"{ \"defaultSwitchState\" : true }"
                    },
                 "propertytypes":
                    {
                     "parameters":"string"
                    },
                 "rotation":0,
                 "type":"",
                 "visible":true,
                 "width":24,
                 "x":64,
                 "y":320
                }, 
                {
                 "gid":2147491199,
                 "height":24,
                 "id":2017,
                 "name":"",
                 "properties":
                    {
                     "parameters":"{ \"defaultSwitchState\" : true }"
                    },
                 "propertytypes":
                    {
                     "parameters":"string"
                    },
                 "rotation":0,
                 "type":"",
                 "visible":true,
                 "width":24,
                 "x":128,
                 "y":320
                }, 
                {
                 "gid":2147491199,
                 "height":24,
                 "id":2018,
                 "name":"",
                 "properties":
                    {
                     "parameters":"{ \"defaultSwitchState\" : true }"
                    },
                 "propertytypes":
                    {
                     "parameters":"string"
                    },
                 "rotation":0,
                 "type":"",
                 "visible":true,
                 "width":24,
                 "x":248,
                 "y":320
                }, 
                {
                 "gid":2147491199,
                 "height":24,
                 "id":2019,
                 "name":"",
                 "properties":
                    {
                     "parameters":"{ \"defaultSwitchState\" : false }"
                    },
                 "propertytypes":
                    {
                     "parameters":"string"
                    },
                 "rotation":0,
                 "type":"",
                 "visible":true,
                 "width":24,
                 "x":272,
                 "y":320
                }, 
                {
                 "gid":2147491168,
                 "height":16,
                 "id":2028,
                 "name":"",
                 "properties":
                    {
                     "parameters":"{ \"defaultSwitchState\" : true }"
                    },
                 "propertytypes":
                    {
                     "parameters":"string"
                    },
                 "rotation":0,
                 "type":"",
                 "visible":true,
                 "width":40,
                 "x":280,
                 "y":368
                }, 
                {
                 "gid":8947,
                 "height":24,
                 "id":2029,
                 "name":"",
                 "rotation":0,
                 "type":"",
                 "visible":true,
                 "width":16,
                 "x":264,
                 "y":368
                }, 
                {
                 "gid":2147492582,
                 "height":24,
                 "id":2031,
                 "name":"",
                 "properties":
                    {
                     "parameters":"{ \"defaultSwitchState\" : true }"
                    },
                 "propertytypes":
                    {
                     "parameters":"string"
                    },
                 "rotation":0,
                 "type":"",
                 "visible":true,
                 "width":24,
                 "x":112,
                 "y":368
                }, 
                {
                 "gid":2147492586,
                 "height":24,
                 "id":2032,
                 "name":"",
                 "rotation":0,
                 "type":"",
                 "visible":true,
                 "width":16,
                 "x":96,
                 "y":368
                }, 
                {
                 "gid":8934,
                 "height":24,
                 "id":2033,
                 "name":"",
                 "properties":
                    {
                     "parameters":"{ \"defaultSwitchState\" : true }"
                    },
                 "propertytypes":
                    {
                     "parameters":"string"
                    },
                 "rotation":0,
                 "type":"",
                 "visible":true,
                 "width":24,
                 "x":72,
                 "y":368
                }, 
                {
                 "gid":6280,
                 "height":8,
                 "id":2083,
                 "name":"",
                 "rotation":0,
                 "type":"",
                 "visible":true,
                 "width":16,
                 "x":352,
                 "y":320
                }, 
                {
                 "gid":210,
                 "height":8,
                 "id":2090,
                 "name":"",
                 "rotation":0,
                 "type":"",
                 "visible":true,
                 "width":8,
                 "x":48,
                 "y":368
                }, 
                {
                 "gid":7038,
                 "height":24,
                 "id":2101,
                 "name":"",
                 "properties":
                    {
                     "parameters":"{\"treasurePools\":[\"spaceChestTreasure\"]}"
                    },
                 "propertytypes":
                    {
                     "parameters":"string"
                    },
                 "rotation":0,
                 "type":"",
                 "visible":true,
                 "width":32,
                 "x":176,
                 "y":312
                }, 
                {
                 "gid":561,
                 "height":16,
                 "id":2102,
                 "name":"",
                 "rotation":0,
                 "type":"",
                 "visible":true,
                 "width":16,
                 "x":184,
                 "y":264
                }, 
                {
                 "gid":2147484209,
                 "height":16,
                 "id":2103,
                 "name":"",
                 "rotation":0,
                 "type":"",
                 "visible":true,
                 "width":16,
                 "x":240,
                 "y":288
                }, 
                {
                 "gid":561,
                 "height":16,
                 "id":2104,
                 "name":"",
                 "rotation":0,
                 "type":"",
                 "visible":true,
                 "width":16,
                 "x":64,
                 "y":288
                }, 
                {
                 "gid":6300,
                 "height":8,
                 "id":2105,
                 "name":"",
                 "rotation":0,
                 "type":"",
                 "visible":true,
                 "width":10,
                 "x":88,
                 "y":280
                }, 
                {
                 "gid":6300,
                 "height":8,
                 "id":2106,
                 "name":"",
                 "rotation":0,
                 "type":"",
                 "visible":true,
                 "width":10,
                 "x":120,
                 "y":280
                }, 
                {
                 "gid":6300,
                 "height":8,
                 "id":2107,
                 "name":"",
                 "rotation":0,
                 "type":"",
                 "visible":true,
                 "width":10,
                 "x":168,
                 "y":256
                }, 
                {
                 "gid":6300,
                 "height":8,
                 "id":2108,
                 "name":"",
                 "rotation":0,
                 "type":"",
                 "visible":true,
                 "width":10,
                 "x":208,
                 "y":256
                }, 
                {
                 "gid":561,
                 "height":16,
                 "id":2109,
                 "name":"",
                 "rotation":0,
                 "type":"",
                 "visible":true,
                 "width":16,
                 "x":296,
                 "y":288
                }, 
                {
                 "gid":792,
                 "height":24,
                 "id":2110,
                 "name":"",
                 "rotation":0,
                 "type":"",
                 "visible":true,
                 "width":32,
                 "x":264,
                 "y":296
                }, 
                {
                 "gid":2147484440,
                 "height":24,
                 "id":2111,
                 "name":"",
                 "rotation":0,
                 "type":"",
                 "visible":true,
                 "width":32,
                 "x":288,
                 "y":352
                }, 
                {
                 "gid":2762,
                 "height":16,
                 "id":2112,
                 "name":"",
                 "rotation":0,
                 "type":"",
                 "visible":true,
                 "width":16,
                 "x":184,
                 "y":376
                }, 
                {
                 "gid":6444,
                 "height":8,
                 "id":2113,
                 "name":"",
                 "rotation":0,
                 "type":"",
                 "visible":true,
                 "width":16,
                 "x":352,
                 "y":328
                }],
         "opacity":1,
         "type":"objectgroup",
         "visible":true,
         "x":0,
         "y":0
        }, 
        {
         "color":"#ffff00",
         "draworder":"topdown",
         "name":"wiring - lights & guns",
         "objects":[],
         "opacity":1,
         "type":"objectgroup",
         "visible":true,
         "x":0,
         "y":0
        }, 
        {
         "color":"#ff0000",
         "draworder":"topdown",
         "name":"monsters & npcs",
         "objects":[
                {
                 "height":8,
                 "id":2085,
                 "name":"",
                 "properties":
                    {
                     "npc":"apex, avian, human, hylotl",
                     "typeName":"brainslugscientisthostile"
                    },
                 "propertytypes":
                    {
                     "npc":"string",
                     "typeName":"string"
                    },
                 "rotation":0,
                 "type":"",
                 "visible":true,
                 "width":8,
                 "x":256,
                 "y":336
                }, 
                {
                 "height":8,
                 "id":2086,
                 "name":"",
                 "properties":
                    {
                     "npc":"apex, avian, human, hylotl",
                     "typeName":"brainslugscientisthostile"
                    },
                 "propertytypes":
                    {
                     "npc":"string",
                     "typeName":"string"
                    },
                 "rotation":0,
                 "type":"",
                 "visible":true,
                 "width":8,
                 "x":104,
                 "y":288
                }, 
                {
                 "height":8,
                 "id":2087,
                 "name":"",
                 "properties":
                    {
                     "npc":"apex, avian, human, hylotl",
                     "typeName":"brainslugscientisthostile"
                    },
                 "propertytypes":
                    {
                     "npc":"string",
                     "typeName":"string"
                    },
                 "rotation":0,
                 "type":"",
                 "visible":true,
                 "width":8,
                 "x":264,
                 "y":288
                }, 
                {
                 "height":8,
                 "id":2114,
                 "name":"",
                 "properties":
                    {
                     "monster":"symbiotecritter"
                    },
                 "propertytypes":
                    {
                     "monster":"string"
                    },
                 "rotation":0,
                 "type":"",
                 "visible":true,
                 "width":8,
                 "x":240,
                 "y":312
                }, 
                {
                 "height":8,
                 "id":2115,
                 "name":"",
                 "properties":
                    {
                     "monster":"symbiotecritter"
                    },
                 "propertytypes":
                    {
                     "monster":"string"
                    },
                 "rotation":0,
                 "type":"",
                 "visible":true,
                 "width":8,
                 "x":120,
                 "y":312
                }, 
                {
                 "height":8,
                 "id":2116,
                 "name":"",
                 "properties":
                    {
                     "monster":"symbiotecritter"
                    },
                 "propertytypes":
                    {
                     "monster":"string"
                    },
                 "rotation":0,
                 "type":"",
                 "visible":true,
                 "width":8,
                 "x":248,
                 "y":360
                }, 
                {
                 "height":8,
                 "id":2117,
                 "name":"",
                 "properties":
                    {
                     "monster":"symbiotecritter"
                    },
                 "propertytypes":
                    {
                     "monster":"string"
                    },
                 "rotation":0,
                 "type":"",
                 "visible":true,
                 "width":8,
                 "x":64,
                 "y":360
                }, 
                {
                 "height":8,
                 "id":2118,
                 "name":"",
                 "properties":
                    {
                     "monster":"symbiotecritter"
                    },
                 "propertytypes":
                    {
                     "monster":"string"
                    },
                 "rotation":0,
                 "type":"",
                 "visible":true,
                 "width":8,
                 "x":192,
                 "y":312
                }],
         "opacity":1,
         "type":"objectgroup",
         "visible":true,
         "x":0,
         "y":0
        }, 
        {
         "color":"#00ffff",
         "draworder":"topdown",
         "name":"wiring - locked door",
         "objects":[],
         "opacity":1,
         "type":"objectgroup",
         "visible":true,
         "x":0,
         "y":0
        }, 
        {
         "draworder":"topdown",
         "name":"outside the map",
         "objects":[],
         "opacity":1,
         "type":"objectgroup",
         "visible":true,
         "x":0,
         "y":0
        }, 
        {
         "draworder":"topdown",
         "name":"anchors etc",
         "objects":[],
         "opacity":1,
         "type":"objectgroup",
         "visible":true,
         "x":0,
         "y":0
        }, 
        {
         "draworder":"topdown",
         "name":"items",
         "objects":[],
         "opacity":1,
         "type":"objectgroup",
         "visible":true,
         "x":0,
         "y":0
        }],
 "nextobjectid":2119,
 "orientation":"orthogonal",
 "renderorder":"right-down",
 "tiledversion":"1.1.1",
 "tileheight":8,
 "tilesets":[
        {
         "firstgid":1,
         "source":"..\/..\/..\/tilesets\/packed\/materials.json"
        }, 
        {
         "firstgid":198,
         "source":"..\/..\/..\/tilesets\/packed\/miscellaneous.json"
        }, 
        {
         "firstgid":222,
         "source":"..\/..\/..\/tilesets\/packed\/liquids.json"
        }, 
        {
         "firstgid":250,
         "source":"..\/..\/..\/tilesets\/packed\/supports.json"
        }, 
        {
         "firstgid":287,
         "source":"..\/..\/..\/tilesets\/packed\/objects-by-race\/generic.json"
        }, 
        {
         "firstgid":2271,
         "source":"..\/..\/..\/tilesets\/packed\/objects-by-race\/ancient.json"
        }, 
        {
         "firstgid":2434,
         "source":"..\/..\/..\/tilesets\/packed\/objects-by-race\/apex.json"
        }, 
        {
         "firstgid":2805,
         "source":"..\/..\/..\/tilesets\/packed\/objects-by-race\/avian.json"
        }, 
        {
         "firstgid":3110,
         "source":"..\/..\/..\/tilesets\/packed\/objects-by-race\/floran.json"
        }, 
        {
         "firstgid":3305,
         "source":"..\/..\/..\/tilesets\/packed\/objects-by-race\/glitch.json"
        }, 
        {
         "firstgid":3531,
         "source":"..\/..\/..\/tilesets\/packed\/objects-by-race\/human.json"
        }, 
        {
         "firstgid":3819,
         "source":"..\/..\/..\/tilesets\/packed\/objects-by-race\/hylotl.json"
        }, 
        {
         "firstgid":4051,
         "source":"..\/..\/..\/tilesets\/packed\/objects-by-race\/novakid.json"
        }, 
        {
         "firstgid":4115,
         "source":"..\/..\/..\/tilesets\/packed\/objects-by-category\/crafting.json"
        }, 
        {
         "firstgid":4195,
         "source":"..\/..\/..\/tilesets\/packed\/objects-by-category\/decorative.json"
        }, 
        {
         "firstgid":5636,
         "source":"..\/..\/..\/tilesets\/packed\/objects-by-category\/door.json"
        }, 
        {
         "firstgid":5768,
         "source":"..\/..\/..\/tilesets\/packed\/objects-by-category\/farmable.json"
        }, 
        {
         "firstgid":5843,
         "source":"..\/..\/..\/tilesets\/packed\/objects-by-category\/furniture.json"
        }, 
        {
         "firstgid":6197,
         "source":"..\/..\/..\/tilesets\/packed\/objects-by-category\/light.json"
        }, 
        {
         "firstgid":6655,
         "source":"..\/..\/..\/tilesets\/packed\/objects-by-category\/other.json"
        }, 
        {
         "firstgid":6967,
         "source":"..\/..\/..\/tilesets\/packed\/objects-by-category\/sapling.json"
        }, 
        {
         "firstgid":6968,
         "source":"..\/..\/..\/tilesets\/packed\/objects-by-category\/spawner.json"
        }, 
        {
         "firstgid":6984,
         "source":"..\/..\/..\/tilesets\/packed\/objects-by-category\/storage.json"
        }, 
        {
         "firstgid":7218,
         "source":"..\/..\/..\/tilesets\/packed\/objects-by-category\/teleporter.json"
        }, 
        {
         "firstgid":7260,
         "source":"..\/..\/..\/tilesets\/packed\/objects-by-category\/tools.json"
        }, 
        {
         "firstgid":7265,
         "source":"..\/..\/..\/tilesets\/packed\/objects-by-category\/trap.json"
        }, 
        {
         "firstgid":7469,
         "source":"..\/..\/..\/tilesets\/packed\/objects-by-category\/wire.json"
        }, 
        {
         "firstgid":7691,
         "source":"..\/..\/..\/tilesets\/packed\/objects-by-type\/container.json"
        }, 
        {
         "firstgid":7976,
         "source":"..\/..\/..\/tilesets\/packed\/objects-by-type\/farmable.json"
        }, 
        {
         "firstgid":8054,
         "source":"..\/..\/..\/tilesets\/packed\/objects-by-type\/loungeable.json"
        }, 
        {
         "firstgid":8335,
         "source":"..\/..\/..\/tilesets\/packed\/objects-by-type\/noisy.json"
        }, 
        {
         "firstgid":8376,
         "source":"..\/..\/..\/tilesets\/packed\/objects-by-type\/teleporter.json"
        }, 
        {
         "firstgid":8403,
         "source":"..\/..\/..\/tilesets\/packed\/objects-by-colonytag\/station.json"
        }, 
        {
         "firstgid":8433,
         "source":"..\/..\/..\/tilesets\/packed\/objects-by-colonytag\/mining.json"
        }, 
        {
         "firstgid":8443,
         "source":"..\/..\/..\/tilesets\/packed\/objects-by-category\/breakable.json"
        }, 
        {
         "firstgid":8753,
         "source":"..\/..\/..\/tilesets\/packed\/objects-by-colonytag\/misc.json"
        }, 
        {
         "firstgid":8921,
         "source":"..\/..\/..\/tilesets\/packed\/objects-by-colonytag\/lunarbase.json"
        }, 
        {
         "firstgid":8945,
         "source":"..\/..\/..\/tilesets\/packed\/objects-by-colonytag\/outpost.json"
        }],
 "tilewidth":8,
 "type":"map",
 "version":1,
 "width":80
}